MANIFEST.in
README.md
setup.py
cbpi/__init__.py
cbpi/cli.py
cbpi/craftbeerpi.py
cbpi/eventbus.py
cbpi/satellite.py
cbpi/websocket.py
cbpi.egg-info/PKG-INFO
cbpi.egg-info/SOURCES.txt
cbpi.egg-info/dependency_links.txt
cbpi.egg-info/entry_points.txt
cbpi.egg-info/requires.txt
cbpi.egg-info/top_level.txt
cbpi/api/__init__.py
cbpi/api/actor.py
cbpi/api/config.py
cbpi/api/decorator.py
cbpi/api/exceptions.py
cbpi/api/extension.py
cbpi/api/kettle_logic.py
cbpi/api/property.py
cbpi/api/sensor.py
cbpi/api/step.py
cbpi/config/actor.json
cbpi/config/config.yaml
cbpi/config/create_database.sql
cbpi/config/kettle.json
cbpi/config/plugin_list.txt
cbpi/config/sensor.json
cbpi/config/splash.png
cbpi/config/step_data.json
cbpi/config/dashboard/cbpi_dashboard_1.json
cbpi/controller/__init__.py
cbpi/controller/actor_controller.py
cbpi/controller/basic_controller.py
cbpi/controller/config_controller.py
cbpi/controller/dashboard_controller.py
cbpi/controller/job_controller.py
cbpi/controller/kettle_controller.py
cbpi/controller/log_file_controller.py
cbpi/controller/notification_controller.py
cbpi/controller/plugin_controller.py
cbpi/controller/sensor_controller.py
cbpi/controller/step_controller.py
cbpi/controller/system_controller.py
cbpi/database/__init__.py
cbpi/database/model.py
cbpi/database/orm_framework.py
cbpi/extension/__init__.py
cbpi/extension/__pycache__/__init__.cpython-37.pyc
cbpi/extension/__pycache__/__init__.cpython-38.pyc
cbpi/extension/comp/__init__.py
cbpi/extension/comp/config.yaml
cbpi/extension/comp/static/index.html
cbpi/extension/comp/static/index2.html
cbpi/extension/ds18b20/__init__.py
cbpi/extension/ds18b20/config.yaml
cbpi/extension/ds18b20/__pycache__/__init__.cpython-37.pyc
cbpi/extension/ds18b20/__pycache__/__init__.cpython-38.pyc
cbpi/extension/dummyactor/__init__.py
cbpi/extension/dummyactor/config.yaml
cbpi/extension/dummyactor/__pycache__/__init__.cpython-37.pyc
cbpi/extension/dummyactor/__pycache__/__init__.cpython-38.pyc
cbpi/extension/dummylogic/__init__.py
cbpi/extension/dummylogic/config.yaml
cbpi/extension/dummylogic/__pycache__/__init__.cpython-37.pyc
