Metadata-Version: 1.0
Name: cbpi
Version: 4.0.0.17
Summary: CraftBeerPi
Home-page: http://web.craftbeerpi.com
Author: Manuel Fritsch
Author-email: manuel@craftbeerpi.com
License: UNKNOWN
Platform: UNKNOWN
